misskey/__init__.py
misskey/misskeyapi.py
MisskeyAPI-0.1.0.dist-info/LICENSE
MisskeyAPI-0.1.0.dist-info/METADATA
MisskeyAPI-0.1.0.dist-info/WHEEL
MisskeyAPI-0.1.0.dist-info/top_level.txt
MisskeyAPI-0.1.0.dist-info/RECORD
