Metadata-Version: 2.1
Name: MisskeyAPI
Version: 0.1.0
Summary: Python wrapper for Misskey API.
Home-page: https://git.mastodont.cat/spla/MisskeyAPI
Author: spla
Author-email: llemena_obrer.0u@icloud.com
Project-URL: Bug Tracker, https://git.mastodont.cat/spla/MisskeyAPI/issues
Keywords: misskey api python wrapper
Classifier: License :: OSI Approved :: GNU General Public License v3 (GPLv3)
Classifier: Topic :: Software Development :: Libraries :: Python Modules
Classifier: Topic :: Communications
Classifier: Intended Audience :: Developers
Classifier: Intended Audience :: System Administrators
Classifier: Topic :: Communications
Classifier: Programming Language :: Python :: 3
Requires-Python: >=3.8
License-File: LICENSE
Requires-Dist: requests
